CHANGELOG
LICENSE
MANIFEST.in
README.rst
TODO
pavement.py
requirements-dev.txt
requirements.txt
setup.py
tox.ini
docs/Makefile
docs/make.bat
docs/source/README
docs/source/conf.py
docs/source/index.rst
docs/source/_static/.gitkeep
spec_checker/__init__.py
spec_checker/default_config.py
spec_checker/designelement.py
spec_checker/main.py
spec_checker/metadata.py
spec_checker/requirement.py
spec_checker/runtime.py
spec_checker/util.py
spec_checker.egg-info/PKG-INFO
spec_checker.egg-info/SOURCES.txt
spec_checker.egg-info/dependency_links.txt
spec_checker.egg-info/entry_points.txt
spec_checker.egg-info/not-zip-safe
spec_checker.egg-info/top_level.txt
tests/test_main.py